LICENCE
README.md
pyproject.toml
setup.cfg
setup.py
ml_jdp4/__init__.py
ml_jdp4/ml_jdp4.py
ml_jdp4.egg-info/PKG-INFO
ml_jdp4.egg-info/SOURCES.txt
ml_jdp4.egg-info/dependency_links.txt
ml_jdp4.egg-info/entry_points.txt
ml_jdp4.egg-info/requires.txt
ml_jdp4.egg-info/top_level.txt
ml_jdp4/data/__init__.py
ml_jdp4/data/krC.dat
ml_jdp4/data/krH.dat
ml_jdp4/examples/__init__.py
ml_jdp4/examples/menthol_ML_dJ-DP4/01_menthol_c1.log
ml_jdp4/examples/menthol_ML_dJ-DP4/01_menthol_c10.log
ml_jdp4/examples/menthol_ML_dJ-DP4/01_menthol_c11.log
ml_jdp4/examples/menthol_ML_dJ-DP4/01_menthol_c12.log
ml_jdp4/examples/menthol_ML_dJ-DP4/01_menthol_c13.log
ml_jdp4/examples/menthol_ML_dJ-DP4/01_menthol_c14.log
ml_jdp4/examples/menthol_ML_dJ-DP4/01_menthol_c15.log
ml_jdp4/examples/menthol_ML_dJ-DP4/01_menthol_c16.log
ml_jdp4/examples/menthol_ML_dJ-DP4/01_menthol_c17.log
ml_jdp4/examples/menthol_ML_dJ-DP4/01_menthol_c18.log
ml_jdp4/examples/menthol_ML_dJ-DP4/01_menthol_c19.log
ml_jdp4/examples/menthol_ML_dJ-DP4/01_menthol_c2.log
ml_jdp4/examples/menthol_ML_dJ-DP4/01_menthol_c20.log
ml_jdp4/examples/menthol_ML_dJ-DP4/01_menthol_c21.log
ml_jdp4/examples/menthol_ML_dJ-DP4/01_menthol_c22.log
ml_jdp4/examples/menthol_ML_dJ-DP4/01_menthol_c23.log
ml_jdp4/examples/menthol_ML_dJ-DP4/01_menthol_c24.log
ml_jdp4/examples/menthol_ML_dJ-DP4/01_menthol_c25.log
ml_jdp4/examples/menthol_ML_dJ-DP4/01_menthol_c26.log
ml_jdp4/examples/menthol_ML_dJ-DP4/01_menthol_c27.log
ml_jdp4/examples/menthol_ML_dJ-DP4/01_menthol_c28.log
ml_jdp4/examples/menthol_ML_dJ-DP4/01_menthol_c29.log
ml_jdp4/examples/menthol_ML_dJ-DP4/01_menthol_c3.log
ml_jdp4/examples/menthol_ML_dJ-DP4/01_menthol_c30.log
ml_jdp4/examples/menthol_ML_dJ-DP4/01_menthol_c31.log
ml_jdp4/examples/menthol_ML_dJ-DP4/01_menthol_c32.log
ml_jdp4/examples/menthol_ML_dJ-DP4/01_menthol_c4.log
ml_jdp4/examples/menthol_ML_dJ-DP4/01_menthol_c5.log
ml_jdp4/examples/menthol_ML_dJ-DP4/01_menthol_c6.log
ml_jdp4/examples/menthol_ML_dJ-DP4/01_menthol_c7.log
ml_jdp4/examples/menthol_ML_dJ-DP4/01_menthol_c8.log
ml_jdp4/examples/menthol_ML_dJ-DP4/01_menthol_c9.log
ml_jdp4/examples/menthol_ML_dJ-DP4/02_menthol_c1.log
