Metadata-Version: 2.1
Name: ml-jdp4
Version: 1.3.2
Summary: An integrated quantum mechanics-machine learning approach for ultra-fast NMR structural elucidation.
Home-page: https://github.com/Sarotti-Lab/ML_J_DP4
Author: María M. Zanardi & Ariel M. Sarotti
Author-email: zanardi@inv.rosario-conicet.gov.ar
License: MIT
Keywords: NMR structural elucidation
Platform: UNKNOWN
Classifier: Programming Language :: Python :: 3
Classifier: License :: OSI Approved :: MIT License
Classifier: Operating System :: OS Independent
License-File: LICENCE
